<?xml version="1.0" encoding="Windows-1252"?>
<MonsterCollection xmlns:xsi="http://www.w3.org/2001/XMLSchema-instance" xmlns:xsd="http://www.w3.org/2001/XMLSchema">
  <list>
    <list level="2" health="200" maxHealth="200" attackPower="15" walkingSpeed="1" location="21.9005089" rotation="0.247492641" isPosioned_x003F_="false" isStunned_x003F_="false" type="Water">
      <location_y>7.00821038E-05</location_y>
      <location_z>-24.7297726</location_z>
      <rotation_x>-0.0001191048</rotation_x>
      <rotation_y>0.968889654</rotation_y>
      <rotation_z>0.000466274068</rotation_z>
    </list>
    <list level="1" health="100" maxHealth="100" attackPower="10" walkingSpeed="2" location="41.0210762" rotation="0.1097167" isPosioned_x003F_="false" isStunned_x003F_="false" type="Wind">
      <location_y>-1.90734863E-06</location_y>
      <location_z>-9.594202</location_z>
      <rotation_x>-4.828684E-05</rotation_x>
      <rotation_y>0.9939628</rotation_y>
      <rotation_z>0.00043744783</rotation_z>
    </list>
  </list>
</MonsterCollection>